qualipy/__init__.py
qualipy/__main__.py
qualipy/authentication/__init__.py
qualipy/authentication/authenticator.py
qualipy/authentication/keyring_authenticator.py
qualipy/config/__init__.py
qualipy/config/app_config.py
qualipy/data_management/__init__.py
qualipy/data_management/csv_data_loader.py
qualipy/data_management/data_loader.py
qualipy/data_management/data_manager.py
qualipy/data_management/excel_data_loader.py
qualipy/data_management/json_data_loader.py
qualipy/data_management/xml_data_loader.py
qualipy/data_management/yaml_data_loader.py
qualipy/exceptions/__init__.py
qualipy/proj_mgmt_plugins/__init__.py
qualipy/proj_mgmt_plugins/jira_proj_mgmt_plugin.py
qualipy/proj_mgmt_plugins/proj_mgmt_plugin.py
qualipy/test_plugins/__init__.py
qualipy/test_plugins/behave_plugin.py
qualipy/test_plugins/test_plugin.py
qualipy-1.1.2.dist-info/LICENSE
qualipy-1.1.2.dist-info/METADATA
qualipy-1.1.2.dist-info/WHEEL
qualipy-1.1.2.dist-info/top_level.txt
qualipy-1.1.2.dist-info/RECORD
