Metadata-Version: 2.1
Name: qualipy
Version: 1.1.2
Summary: Automated test process framework
Author-email: Charles Morris <cmorris616@gmail.com>
Project-URL: Homepage, https://github.com/cmorris616/qualipy
Project-URL: Bug Tracker, https://github.com/cmorris616/qualipy/issues
Project-URL: Documentation, https://cmorris-qualipy.readthedocs.io/en/stable
Keywords: test,testing,project management,jira,framework
Classifier: Programming Language :: Python :: 3
Classifier: License :: OSI Approved :: MIT License
Classifier: Operating System :: OS Independent
Requires-Python: >=3.7
License-File: LICENSE
Requires-Dist: behave
Requires-Dist: keyring
Requires-Dist: requests
Requires-Dist: PyYAML
Requires-Dist: openpyxl
